sample_loggers-0.0.5.dist-info/METADATA
sample_loggers-0.0.5.dist-info/WHEEL
sample_loggers-0.0.5.dist-info/entry_points.txt
sample_loggers/__init__.py
sample_loggers/config.py
sample_loggers/logger.py
sample_loggers/utils.py
sample_loggers/version.py
sample_loggers-0.0.5.dist-info/RECORD
