Metadata-Version: 2.1
Name: sample_loggers
Version: 0.0.5
Summary: This package provides sample loggers.
Keywords: python,tools,logger
Author-Email: Ian Zhu <IanZhu@m.ldu.edu.cn>
License: MIT
Project-URL: homepage, https://github.com/10-4zz/sample_loggers.git
Project-URL: repository, https://github.com/10-4zz/sample_loggers.git
Requires-Python: >=3.9
Requires-Dist: termcolor
Requires-Dist: yacs
